[{"district":"NO. CALIFORNIA","flight":"","level":"3.5","loser":"Bob Yee, Edward Y. Lee","matchDate":"4/3/2011","matchId":"1002198933","matchType":"#2 Doubles","name":"2011 Upper Peninsula Adult Leagues","round":"","score":"6-2, 6-1","section":"USTA/NO. CALIFORNIA","type":"Local League","winner":"Gene H Cherng, Earl A Prack"},{"district":"NO. CALIFORNIA","flight":"","level":"3.5","loser":"Gene H Cherng, Earl A Prack","matchDate":"4/17/2011","matchId":"1002198947","matchType":"#2 Doubles","name":"2011 Upper Peninsula Adult Leagues","round":"","score":"0-6, 6-4, 1-0","section":"USTA/NO. CALIFORNIA","type":"Local League","winner":"Michael Rudolph, John Knowles Dyer"},{"district":"NO. CALIFORNIA","flight":"","level":"3.5","loser":"Dick Heiman, H. G. Tower","matchDate":"4/19/2011","matchId":"1002198955","matchType":"#2 Doubles","name":"2011 Upper Peninsula Adult Leagues","round":"","score":"5-7, 6-3, 1-0","section":"USTA/NO. CALIFORNIA","type":"Local League","winner":"Earl A Prack, Gene H Cherng"},{"district":"NO. CALIFORNIA","flight":"","level":"3.5","loser":"Gene H Cherng, Earl A Prack","matchDate":"5/19/2011","matchId":"1002198987","matchType":"#1 Doubles","name":"2011 Upper Peninsula Adult Leagues","round":"","score":"6-2, 6-2","section":"USTA/NO. CALIFORNIA","type":"Local League","winner":"Darryle Isaac, Marc Passen"},{"district":"NO. CALIFORNIA","flight":"","level":"3.5","loser":"Peter Watkins","matchDate":"5/25/2011","matchId":"1002198994","matchType":"#2 Singles","name":"2011 Upper Peninsula Adult Leagues","round":"","score":"6-2, 6-2","section":"USTA/NO. CALIFORNIA","type":"Local League","winner":"Gene H Cherng"},{"district":"NO. CALIFORNIA","flight":"","level":"3.5","loser":"Michael Stafford","matchDate":"6/5/2011","matchId":"1002199000","matchType":"#1 Singles","name":"2011 Upper Peninsula Adult Leagues","round":"","score":"6-2, 3-6, 1-0","section":"USTA/NO. CALIFORNIA","type":"Local League","winner":"Gene H Cherng"},{"district":"NO. CALIFORNIA","flight":"","level":"3.5","loser":"Jeffrey Michael Schubiner","matchDate":"6/8/2011","matchId":"1002199006","matchType":"#1 Singles","name":"2011 Upper Peninsula Adult Leagues","round":"","score":"7-5, 6-3","section":"USTA/NO. CALIFORNIA","type":"Local League","winner":"Gene H Cherng"},{"district":"NO. CALIFORNIA","flight":"","level":"3.5","loser":"Scott Reid","matchDate":"6/19/2011","matchId":"1002199012","matchType":"#1 Singles","name":"2011 Upper Peninsula Adult Leagues","round":"","score":"6-1, 6-2","section":"USTA/NO. CALIFORNIA","type":"Local League","winner":"Gene H Cherng"},{"district":"NO. CALIFORNIA","flight":"","level":"3.5","loser":"ditson solomon hendricks","matchDate":"7/14/2011","matchId":"1002441381","matchType":"#1 Singles","name":"2011 Upper Peninsula Adult Leagues","round":"","score":"6-3, 6-4","section":"USTA/NO. CALIFORNIA","type":"Local League","winner":"Gene H Cherng"},{"district":"","flight":"District","level":"Adult / 3.5 / M","loser":"Gene H Cherng","matchDate":"8/12/2011","matchId":"2347870","matchType":"#1 Singles","name":"NO. CALIFORNIA District Championship / Flight 3","round":"","score":"6-4, 6-4","section":"","type":"Championship","winner":"Carlos Javier Del Rio Villasenor"},{"district":"","flight":"District","level":"Adult / 3.5 / M","loser":"Gene H Cherng","matchDate":"8/13/2011","matchId":"2347868","matchType":"#1 Singles","name":"NO. CALIFORNIA District Championship / Flight 3","round":"","score":"6-2, 7-5","section":"","type":"Championship","winner":"Jonathan C. Maze"}]